{"label":"round_103","startBlock":18334566,"endBlock":18786471,"govWeightThreshold":500,"donutUpvoterTotalReward":340000,"quadRankTotalReward":680000,"rewards":[{"username":"JohnFrontino","points":120,"contributor_type":"donut_upvoter"},{"username":"InevitableComplex895","points":14924,"contributor_type":"donut_upvoter"},{"username":"Suthekingg","points":12637,"contributor_type":"donut_upvoter"},{"username":"raymv1987","points":3851,"contributor_type":"donut_upvoter"},{"username":"Basoosh","points":8665,"contributor_type":"donut_upvoter"},{"username":"Buzz_Sensei","points":19377,"contributor_type":"donut_upvoter"},{"username":"roymustang261","points":2046,"contributor_type":"donut_upvoter"},{"username":"Soaring_Eagle590","points":7342,"contributor_type":"donut_upvoter"},{"username":"karan51ngh","points":120,"contributor_type":"donut_upvoter"},{"username":"13illini","points":602,"contributor_type":"donut_upvoter"},{"username":"carlslarson","points":481,"contributor_type":"donut_upvoter"},{"username":"ETHWarrior0","points":241,"contributor_type":"donut_upvoter"},{"username":"Jake123194","points":1083,"contributor_type":"donut_upvoter"},{"username":"ethereum88","points":13119,"contributor_type":"donut_upvoter"},{"username":"TenCoinsShort","points":14081,"contributor_type":"donut_upvoter"},{"username":"Hastyrunner245","points":3009,"contributor_type":"donut_upvoter"},{"username":"Acceptable-Sort-8429","points":3851,"contributor_type":"donut_upvoter"},{"username":"spacsandspacs","points":2648,"contributor_type":"donut_upvoter"},{"username":"kohrts","points":2407,"contributor_type":"donut_upvoter"},{"username":"RayG1991","points":2648,"contributor_type":"donut_upvoter"},{"username":"adamix244","points":8184,"contributor_type":"donut_upvoter"},{"username":"ejdunia","points":3370,"contributor_type":"donut_upvoter"},{"username":"Primary_Ground_3858","points":41642,"contributor_type":"donut_upvoter"},{"username":"greenmansavinglives","points":2046,"contributor_type":"donut_upvoter"},{"username":"420weedscopes","points":481,"contributor_type":"donut_upvoter"},{"username":"Jerry200px","points":1805,"contributor_type":"donut_upvoter"},{"username":"1894Harold","points":8184,"contributor_type":"donut_upvoter"},{"username":"skj4ua","points":481,"contributor_type":"donut_upvoter"},{"username":"sirjakobos","points":5296,"contributor_type":"donut_upvoter"},{"username":"camp2gg","points":241,"contributor_type":"donut_upvoter"},{"username":"Samir2298","points":1926,"contributor_type":"donut_upvoter"},{"username":"furysammy","points":44411,"contributor_type":"donut_upvoter"},{"username":"pc1e0","points":120,"contributor_type":"donut_upvoter"},{"username":"rustedpopcorn","points":1083,"contributor_type":"donut_upvoter"},{"username":"fitbhai","points":8304,"contributor_type":"donut_upvoter"},{"username":"The_Nutcrack","points":17933,"contributor_type":"donut_upvoter"},{"username":"aminok","points":361,"contributor_type":"donut_upvoter"},{"username":"Aim_Sux","points":3129,"contributor_type":"donut_upvoter"},{"username":"Arafel_Electronics","points":241,"contributor_type":"donut_upvoter"},{"username":"UrMuMGaEe","points":120,"contributor_type":"donut_upvoter"},{"username":"itsckomi","points":120,"contributor_type":"donut_upvoter"},{"username":"SxQuadro","points":1805,"contributor_type":"donut_upvoter"},{"username":"killawaspattack","points":120,"contributor_type":"donut_upvoter"},{"username":"Grouchy-Jellyfish267","points":14322,"contributor_type":"donut_upvoter"},{"username":"sartoshi_nft","points":9147,"contributor_type":"donut_upvoter"},{"username":"ethereumgasbot","points":12758,"contributor_type":"donut_upvoter"},{"username":"comfyggs","points":120,"contributor_type":"donut_upvoter"},{"username":"fodes96","points":722,"contributor_type":"donut_upvoter"},{"username":"ethovian08","points":241,"contributor_type":"donut_upvoter"},{"username":"MicThess","points":37791,"contributor_type":"donut_upvoter"},{"username":"ghochumal","points":241,"contributor_type":"donut_upvoter"},{"username":"Suthekingg","points":9147,"contributor_type":"quad_rank"},{"username":"Nice-Veterinarian-28","points":41,"contributor_type":"quad_rank"},{"username":"spacsandspacs","points":8826,"contributor_type":"quad_rank"},{"username":"bitcoinsky","points":41,"contributor_type":"quad_rank"},{"username":"alexo12","points":10927,"contributor_type":"quad_rank"},{"username":"bzzking","points":13360,"contributor_type":"quad_rank"},{"username":"greenpepperhypernova","points":4968,"contributor_type":"quad_rank"},{"username":"getblockio","points":901,"contributor_type":"quad_rank"},{"username":"adamix244","points":12333,"contributor_type":"quad_rank"},{"username":"Jake123194","points":5598,"contributor_type":"quad_rank"},{"username":"Crypto_Gaming_","points":15990,"contributor_type":"quad_rank"},{"username":"TogetherWeHappy","points":9829,"contributor_type":"quad_rank"},{"username":"EthTraderCommunity","points":12253,"contributor_type":"quad_rank"},{"username":"devboricha","points":577,"contributor_type":"quad_rank"},{"username":"Paper_cobbler","points":1645,"contributor_type":"quad_rank"},{"username":"Innit4theTech","points":13266,"contributor_type":"quad_rank"},{"username":"InevitableComplex895","points":21765,"contributor_type":"quad_rank"},{"username":"Genius02","points":72,"contributor_type":"quad_rank"},{"username":"SufficientMonkey","points":2202,"contributor_type":"quad_rank"},{"username":"Defiboy","points":4642,"contributor_type":"quad_rank"},{"username":"bigmammoth2310","points":5457,"contributor_type":"quad_rank"},{"username":"Fifth_Libation","points":84,"contributor_type":"quad_rank"},{"username":"ejdunia","points":6779,"contributor_type":"quad_rank"},{"username":"bullishoneth","points":2940,"contributor_type":"quad_rank"},{"username":"GertrudKirksey","points":617,"contributor_type":"quad_rank"},{"username":"OwnSession9","points":617,"contributor_type":"quad_rank"},{"username":"cryptbunks","points":4113,"contributor_type":"quad_rank"},{"username":"MaximalAnarchy","points":6212,"contributor_type":"quad_rank"},{"username":"Soaring_Eagle590","points":6594,"contributor_type":"quad_rank"},{"username":"Artificial8Wanderer","points":2630,"contributor_type":"quad_rank"},{"username":"ethereum88","points":23291,"contributor_type":"quad_rank"},{"username":"Buzz_Sensei","points":11503,"contributor_type":"quad_rank"},{"username":"rayQuGR","points":3377,"contributor_type":"quad_rank"},{"username":"irokrvulsantv5","points":851,"contributor_type":"quad_rank"},{"username":"cryptopunk661","points":2829,"contributor_type":"quad_rank"},{"username":"WenLambo777","points":8076,"contributor_type":"quad_rank"},{"username":"Basoosh","points":7349,"contributor_type":"quad_rank"},{"username":"conscious4400","points":5367,"contributor_type":"quad_rank"},{"username":"SxQuadro","points":14463,"contributor_type":"quad_rank"},{"username":"diggipiggi","points":1843,"contributor_type":"quad_rank"},{"username":"Grouchy-Jellyfish267","points":3195,"contributor_type":"quad_rank"},{"username":"DegreeBroad2250","points":2786,"contributor_type":"quad_rank"},{"username":"coinmonks","points":608,"contributor_type":"quad_rank"},{"username":"Longjumping_Cod_1487","points":1089,"contributor_type":"quad_rank"},{"username":"MrCantPlayGuitar","points":931,"contributor_type":"quad_rank"},{"username":"Cryptocove254","points":120,"contributor_type":"quad_rank"},{"username":"Primary_Ground_3858","points":11516,"contributor_type":"quad_rank"},{"username":"sartoshi_nft","points":7634,"contributor_type":"quad_rank"},{"username":"getitin247","points":120,"contributor_type":"quad_rank"},{"username":"Jimbotastic777","points":247,"contributor_type":"quad_rank"},{"username":"RayG1991","points":4675,"contributor_type":"quad_rank"},{"username":"JayFab6061","points":178,"contributor_type":"quad_rank"},{"username":"Sakright448","points":760,"contributor_type":"quad_rank"},{"username":"ReitHodlr","points":5407,"contributor_type":"quad_rank"},{"username":"economicsdesign","points":617,"contributor_type":"quad_rank"},{"username":"seraglio226","points":91,"contributor_type":"quad_rank"},{"username":"willfords007","points":327,"contributor_type":"quad_rank"},{"username":"Humble-Grape1012","points":5974,"contributor_type":"quad_rank"},{"username":"Imaginary-Adagio2231","points":5102,"contributor_type":"quad_rank"},{"username":"Stoffmeister31","points":120,"contributor_type":"quad_rank"},{"username":"Meowcat34","points":210,"contributor_type":"quad_rank"},{"username":"whiteninja123","points":120,"contributor_type":"quad_rank"},{"username":"LoveMeSumETH","points":9052,"contributor_type":"quad_rank"},{"username":"Entire_Tree5894","points":3899,"contributor_type":"quad_rank"},{"username":"MoldyCheesey","points":2234,"contributor_type":"quad_rank"},{"username":"WilliamThaKhan","points":120,"contributor_type":"quad_rank"},{"username":"killawaspattack","points":793,"contributor_type":"quad_rank"},{"username":"Tatakae69","points":191,"contributor_type":"quad_rank"},{"username":"anotherone1886","points":29,"contributor_type":"quad_rank"},{"username":"bmahbub","points":2664,"contributor_type":"quad_rank"},{"username":"gustavossj","points":3211,"contributor_type":"quad_rank"},{"username":"666CryptoGod420","points":4355,"contributor_type":"quad_rank"},{"username":"wolfpackofwallst","points":41,"contributor_type":"quad_rank"},{"username":"Major_Bandicoot_3239","points":181,"contributor_type":"quad_rank"},{"username":"Signal_Fire7","points":132,"contributor_type":"quad_rank"},{"username":"90s_kidddd","points":91,"contributor_type":"quad_rank"},{"username":"Aim_Sux","points":3835,"contributor_type":"quad_rank"},{"username":"_613_","points":91,"contributor_type":"quad_rank"},{"username":"Roy1984","points":2646,"contributor_type":"quad_rank"},{"username":"Sad-Gazelle-3985","points":91,"contributor_type":"quad_rank"},{"username":"anthony_blues","points":3220,"contributor_type":"quad_rank"},{"username":"JoblessJessica","points":655,"contributor_type":"quad_rank"},{"username":"Weekly-Boot-5063","points":403,"contributor_type":"quad_rank"},{"username":"viksaini97","points":2153,"contributor_type":"quad_rank"},{"username":"furysammy","points":5809,"contributor_type":"quad_rank"},{"username":"Impossible-Ask4646","points":164,"contributor_type":"quad_rank"},{"username":"PoojaaPriyaa","points":1519,"contributor_type":"quad_rank"},{"username":"carlslarson","points":1971,"contributor_type":"quad_rank"},{"username":"johnzander1","points":5281,"contributor_type":"quad_rank"},{"username":"Lord-Nagafen","points":164,"contributor_type":"quad_rank"},{"username":"disruptalot","points":164,"contributor_type":"quad_rank"},{"username":"raymv1987","points":10971,"contributor_type":"quad_rank"},{"username":"Acceptable-Sort-8429","points":4271,"contributor_type":"quad_rank"},{"username":"rich_kaiji","points":164,"contributor_type":"quad_rank"},{"username":"skj4ua","points":546,"contributor_type":"quad_rank"},{"username":"fitbhai","points":165,"contributor_type":"quad_rank"},{"username":"Xmarsbarz","points":91,"contributor_type":"quad_rank"},{"username":"comfyggs","points":3539,"contributor_type":"quad_rank"},{"username":"AnotherMillenial93","points":29,"contributor_type":"quad_rank"},{"username":"greenmansavinglives","points":3434,"contributor_type":"quad_rank"},{"username":"El-Coco-No","points":1962,"contributor_type":"quad_rank"},{"username":"ethereumgasbot","points":6574,"contributor_type":"quad_rank"},{"username":"Bildozer1909","points":764,"contributor_type":"quad_rank"},{"username":"ColdWarCats","points":164,"contributor_type":"quad_rank"},{"username":"chatlourd","points":164,"contributor_type":"quad_rank"},{"username":"nice2yz","points":690,"contributor_type":"quad_rank"},{"username":"getwellsoonAngelie","points":690,"contributor_type":"quad_rank"},{"username":"twicrates","points":5718,"contributor_type":"quad_rank"},{"username":"thetraderlosesitall","points":2882,"contributor_type":"quad_rank"},{"username":"yokesh351","points":1779,"contributor_type":"quad_rank"},{"username":"TRAcademy","points":600,"contributor_type":"quad_rank"},{"username":"Hikarii77","points":771,"contributor_type":"quad_rank"},{"username":"QuizureII","points":2347,"contributor_type":"quad_rank"},{"username":"1894Harold","points":1728,"contributor_type":"quad_rank"},{"username":"sirjakobos","points":1604,"contributor_type":"quad_rank"},{"username":"The_Nutcrack","points":6117,"contributor_type":"quad_rank"},{"username":"DonnieBrast","points":1023,"contributor_type":"quad_rank"},{"username":"chapogrown","points":91,"contributor_type":"quad_rank"},{"username":"Cramsteems","points":795,"contributor_type":"quad_rank"},{"username":"0xholdthedoor","points":1519,"contributor_type":"quad_rank"},{"username":"Massive-Tension-1055","points":617,"contributor_type":"quad_rank"},{"username":"Educational-Spread41","points":922,"contributor_type":"quad_rank"},{"username":"Introvertive_Crawler","points":164,"contributor_type":"quad_rank"},{"username":"J66kson66","points":164,"contributor_type":"quad_rank"},{"username":"Tanvir5012","points":600,"contributor_type":"quad_rank"},{"username":"DaddyCardano","points":600,"contributor_type":"quad_rank"},{"username":"mrsenthil","points":1225,"contributor_type":"quad_rank"},{"username":"roymustang261","points":460,"contributor_type":"quad_rank"},{"username":"Puddingbuks26","points":91,"contributor_type":"quad_rank"},{"username":"naji102","points":6385,"contributor_type":"quad_rank"},{"username":"In_Crust_We_Trust397","points":163,"contributor_type":"quad_rank"},{"username":"RabidSalmon","points":6614,"contributor_type":"quad_rank"},{"username":"terp_studios","points":2818,"contributor_type":"quad_rank"},{"username":"gulasch_man","points":247,"contributor_type":"quad_rank"},{"username":"TheDefiantNews","points":896,"contributor_type":"quad_rank"},{"username":"MostPopularDude","points":2006,"contributor_type":"quad_rank"},{"username":"ExtensionSinger4154","points":563,"contributor_type":"quad_rank"},{"username":"aspiras213","points":164,"contributor_type":"quad_rank"},{"username":"CeresCrypto","points":164,"contributor_type":"quad_rank"},{"username":"socalquest","points":9521,"contributor_type":"quad_rank"},{"username":"Abdulmujeeb98","points":753,"contributor_type":"quad_rank"},{"username":"Enkiduthebeast","points":600,"contributor_type":"quad_rank"},{"username":"elijahebanks","points":1009,"contributor_type":"quad_rank"},{"username":"rootpl","points":322,"contributor_type":"quad_rank"},{"username":"zagesquire","points":1103,"contributor_type":"quad_rank"},{"username":"LostMyPPMs","points":4786,"contributor_type":"quad_rank"},{"username":"Wolfram_George","points":154,"contributor_type":"quad_rank"},{"username":"cwaffle","points":652,"contributor_type":"quad_rank"},{"username":"papabosscomics","points":91,"contributor_type":"quad_rank"},{"username":"TheEtherOracle","points":91,"contributor_type":"quad_rank"},{"username":"maferase","points":91,"contributor_type":"quad_rank"},{"username":"AmbitiousInnvestor","points":247,"contributor_type":"quad_rank"},{"username":"dolleypeey","points":617,"contributor_type":"quad_rank"},{"username":"Pharm-boi","points":29,"contributor_type":"quad_rank"},{"username":"UIIOIIU","points":1793,"contributor_type":"quad_rank"},{"username":"Schwammosaurus_Rex","points":2300,"contributor_type":"quad_rank"},{"username":"Entire_Philosopher_3","points":1610,"contributor_type":"quad_rank"},{"username":"travelguy23","points":617,"contributor_type":"quad_rank"},{"username":"Fluid_Department_120","points":8570,"contributor_type":"quad_rank"},{"username":"somewhat_good","points":1519,"contributor_type":"quad_rank"},{"username":"Many_Arm7466","points":2325,"contributor_type":"quad_rank"},{"username":"homrqt","points":247,"contributor_type":"quad_rank"},{"username":"ClippTube","points":1519,"contributor_type":"quad_rank"},{"username":"aminok","points":2290,"contributor_type":"quad_rank"},{"username":"bdinu89","points":779,"contributor_type":"quad_rank"},{"username":"wee_d","points":617,"contributor_type":"quad_rank"},{"username":"utter_failure88","points":181,"contributor_type":"quad_rank"},{"username":"AdvanceSafe4879","points":1234,"contributor_type":"quad_rank"},{"username":"missmaxalot","points":617,"contributor_type":"quad_rank"},{"username":"Evil_switch","points":617,"contributor_type":"quad_rank"},{"username":"HorrorBrush","points":1012,"contributor_type":"quad_rank"},{"username":"Zealousideal_Ice8918","points":486,"contributor_type":"quad_rank"},{"username":"UrMuMGaEe","points":5298,"contributor_type":"quad_rank"},{"username":"chilocheese","points":2091,"contributor_type":"quad_rank"},{"username":"annoyedpencil","points":1126,"contributor_type":"quad_rank"},{"username":"SoonMoonn","points":1384,"contributor_type":"quad_rank"},{"username":"Rase789","points":152,"contributor_type":"quad_rank"},{"username":"TobiHovey","points":435,"contributor_type":"quad_rank"},{"username":"gibro94","points":152,"contributor_type":"quad_rank"},{"username":"basic_user321","points":152,"contributor_type":"quad_rank"},{"username":"Anna_198808","points":152,"contributor_type":"quad_rank"},{"username":"thatonedude2009","points":152,"contributor_type":"quad_rank"},{"username":"Tyler5508","points":820,"contributor_type":"quad_rank"},{"username":"pcvcolin","points":409,"contributor_type":"quad_rank"},{"username":"DarkestChaos","points":164,"contributor_type":"quad_rank"},{"username":"akejavel","points":410,"contributor_type":"quad_rank"},{"username":"ComprehensiveLab7591","points":6942,"contributor_type":"quad_rank"},{"username":"Low-Ear4034","points":163,"contributor_type":"quad_rank"},{"username":"kaleis007","points":4033,"contributor_type":"quad_rank"},{"username":"sonie90","points":669,"contributor_type":"quad_rank"},{"username":"jhomarcordova","points":152,"contributor_type":"quad_rank"},{"username":"Tylerjordan1994","points":1089,"contributor_type":"quad_rank"},{"username":"Learn2swim2","points":247,"contributor_type":"quad_rank"},{"username":"greeenbeanzzz","points":120,"contributor_type":"quad_rank"},{"username":"Cryptonault","points":998,"contributor_type":"quad_rank"},{"username":"Mattelambo","points":304,"contributor_type":"quad_rank"},{"username":"Common_wisdoms","points":850,"contributor_type":"quad_rank"},{"username":"Lenoe85","points":803,"contributor_type":"quad_rank"},{"username":"Pickinanameainteasy","points":677,"contributor_type":"quad_rank"},{"username":"Salvo523","points":205,"contributor_type":"quad_rank"},{"username":"Skeletonsclique","points":205,"contributor_type":"quad_rank"},{"username":"GilaMonsterMoney","points":205,"contributor_type":"quad_rank"},{"username":"thumbsdrivesmecrazy","points":205,"contributor_type":"quad_rank"},{"username":"bordoisse","points":324,"contributor_type":"quad_rank"},{"username":"JannaReuther","points":164,"contributor_type":"quad_rank"},{"username":"Expensive_Coyote6301","points":253,"contributor_type":"quad_rank"},{"username":"Naeril_HS","points":126,"contributor_type":"quad_rank"},{"username":"Agentgwg","points":126,"contributor_type":"quad_rank"},{"username":"glitznglam05bt","points":492,"contributor_type":"quad_rank"},{"username":"NoGround1510","points":126,"contributor_type":"quad_rank"},{"username":"SubstantialPost4503","points":290,"contributor_type":"quad_rank"},{"username":"jaysal555","points":126,"contributor_type":"quad_rank"},{"username":"user_Q","points":290,"contributor_type":"quad_rank"},{"username":"sakura_oo8","points":126,"contributor_type":"quad_rank"},{"username":"Common-Fisherman8269","points":90,"contributor_type":"quad_rank"},{"username":"PCnerd1024","points":90,"contributor_type":"quad_rank"},{"username":"Electronic_Cup_4825","points":152,"contributor_type":"quad_rank"},{"username":"AbsolutBadLad","points":6346,"contributor_type":"quad_rank"},{"username":"Targerian-King","points":152,"contributor_type":"quad_rank"},{"username":"Scjtchuck","points":91,"contributor_type":"quad_rank"},{"username":"SoheilPakpour","points":164,"contributor_type":"quad_rank"},{"username":"Mr_bike","points":3021,"contributor_type":"quad_rank"},{"username":"Xch4vez","points":246,"contributor_type":"quad_rank"},{"username":"MDiffenbakh","points":126,"contributor_type":"quad_rank"},{"username":"Mosey_13","points":518,"contributor_type":"quad_rank"},{"username":"vanchicko","points":743,"contributor_type":"quad_rank"},{"username":"Visible-Ad743","points":530,"contributor_type":"quad_rank"},{"username":"Alapac0","points":253,"contributor_type":"quad_rank"},{"username":"ZucchiniVegetable485","points":126,"contributor_type":"quad_rank"},{"username":"EliseoSpurrier","points":126,"contributor_type":"quad_rank"},{"username":"Egrego1","points":126,"contributor_type":"quad_rank"},{"username":"Desperate_Day_8813","points":3413,"contributor_type":"quad_rank"},{"username":"spiffyXD","points":278,"contributor_type":"quad_rank"},{"username":"Classic-Ad-810","points":278,"contributor_type":"quad_rank"},{"username":"hugoe11","points":126,"contributor_type":"quad_rank"},{"username":"The-Techie","points":126,"contributor_type":"quad_rank"},{"username":"thefoodboylover","points":587,"contributor_type":"quad_rank"},{"username":"SuperDonutMan23","points":271,"contributor_type":"quad_rank"},{"username":"Tjaaark","points":253,"contributor_type":"quad_rank"},{"username":"Onelinersandblues","points":126,"contributor_type":"quad_rank"},{"username":"Shot_Dragonfruit_326","points":480,"contributor_type":"quad_rank"},{"username":"ShotBot","points":1410,"contributor_type":"quad_rank"},{"username":"bobongoloxo","points":737,"contributor_type":"quad_rank"},{"username":"Head-Rub5761","points":205,"contributor_type":"quad_rank"},{"username":"diarpiiiii","points":891,"contributor_type":"quad_rank"},{"username":"KermitTheFrogo01","points":217,"contributor_type":"quad_rank"},{"username":"tmcndrw","points":91,"contributor_type":"quad_rank"},{"username":"OnlyFarmers","points":126,"contributor_type":"quad_rank"},{"username":"avacado_nutz","points":253,"contributor_type":"quad_rank"},{"username":"i_will_yeet","points":120,"contributor_type":"quad_rank"},{"username":"Perin_Sofia886","points":191,"contributor_type":"quad_rank"},{"username":"Pandora_Key","points":2351,"contributor_type":"quad_rank"},{"username":"aek427","points":120,"contributor_type":"quad_rank"},{"username":"gifeur","points":2288,"contributor_type":"quad_rank"},{"username":"inside_eren_TR","points":726,"contributor_type":"quad_rank"},{"username":"olnamer","points":164,"contributor_type":"quad_rank"},{"username":"ib2sharp","points":126,"contributor_type":"quad_rank"},{"username":"Numerous-Waltz6260","points":870,"contributor_type":"quad_rank"},{"username":"ALiteralHamSandwich","points":990,"contributor_type":"quad_rank"},{"username":"Mr_Qwertyass","points":126,"contributor_type":"quad_rank"},{"username":"Robertomuriithi","points":617,"contributor_type":"quad_rank"},{"username":"akaifox","points":164,"contributor_type":"quad_rank"},{"username":"ForeverWise340","points":164,"contributor_type":"quad_rank"},{"username":"Live-Scar6163","points":11445,"contributor_type":"quad_rank"},{"username":"zmlari","points":617,"contributor_type":"quad_rank"},{"username":"BariBrunton","points":1255,"contributor_type":"quad_rank"},{"username":"rootslane","points":164,"contributor_type":"quad_rank"},{"username":"wmredditor","points":163,"contributor_type":"quad_rank"},{"username":"jtsai943","points":154,"contributor_type":"quad_rank"},{"username":"Yinyangkarma060910","points":682,"contributor_type":"quad_rank"},{"username":"EmelineSeverance","points":162,"contributor_type":"quad_rank"},{"username":"plabon353","points":779,"contributor_type":"quad_rank"},{"username":"sheetsjohn16","points":326,"contributor_type":"quad_rank"},{"username":"Walla_Walla_26","points":617,"contributor_type":"quad_rank"},{"username":"verity519","points":2525,"contributor_type":"quad_rank"},{"username":"Akucera","points":617,"contributor_type":"quad_rank"},{"username":"dunerim","points":617,"contributor_type":"quad_rank"},{"username":"SameBoyHere","points":781,"contributor_type":"quad_rank"},{"username":"ETHWarrior0","points":1000,"contributor_type":"quad_rank"},{"username":"Nitramite","points":401,"contributor_type":"quad_rank"},{"username":"amretardmonke","points":677,"contributor_type":"quad_rank"},{"username":"Oksana222","points":164,"contributor_type":"quad_rank"},{"username":"Ok-Jellyfish6999","points":164,"contributor_type":"quad_rank"},{"username":"reddotarae51","points":890,"contributor_type":"quad_rank"},{"username":"DoreenLi","points":247,"contributor_type":"quad_rank"},{"username":"Linweil_Impact2630","points":247,"contributor_type":"quad_rank"},{"username":"buttcoin_lol","points":247,"contributor_type":"quad_rank"},{"username":"christianjpberg","points":1478,"contributor_type":"quad_rank"},{"username":"Low_Appearance8067","points":164,"contributor_type":"quad_rank"},{"username":"ponder_that","points":994,"contributor_type":"quad_rank"},{"username":"Gh0sta","points":519,"contributor_type":"quad_rank"},{"username":"fodes96","points":3038,"contributor_type":"quad_rank"},{"username":"ProudWeekend6","points":617,"contributor_type":"quad_rank"},{"username":"dont_forget_canada","points":318,"contributor_type":"quad_rank"},{"username":"BrianAtSantiment","points":164,"contributor_type":"quad_rank"},{"username":"Icy-Order-3200","points":164,"contributor_type":"quad_rank"},{"username":"Pupupachu24","points":164,"contributor_type":"quad_rank"},{"username":"Vezuvio","points":164,"contributor_type":"quad_rank"},{"username":"Prof_Void","points":1677,"contributor_type":"quad_rank"},{"username":"MrBone66","points":617,"contributor_type":"quad_rank"},{"username":"Plnetsde2","points":1581,"contributor_type":"quad_rank"},{"username":"HistoricallyMeans","points":91,"contributor_type":"quad_rank"},{"username":"UranusisGolden","points":771,"contributor_type":"quad_rank"},{"username":"PhilDesenex","points":550,"contributor_type":"quad_rank"},{"username":"kohrts","points":3718,"contributor_type":"quad_rank"},{"username":"Crypto_Express","points":191,"contributor_type":"quad_rank"},{"username":"yeyezhang","points":72,"contributor_type":"quad_rank"},{"username":"enlightenedTop","points":762,"contributor_type":"quad_rank"},{"username":"BuddhaIvan","points":2655,"contributor_type":"quad_rank"},{"username":"jrshockley1s","points":164,"contributor_type":"quad_rank"},{"username":"dragonbenj","points":411,"contributor_type":"quad_rank"},{"username":"91n60","points":164,"contributor_type":"quad_rank"},{"username":"LeomaDegnan","points":961,"contributor_type":"quad_rank"},{"username":"scablime","points":236,"contributor_type":"quad_rank"},{"username":"CryptoCNewsBot","points":2093,"contributor_type":"quad_rank"},{"username":"EARTH2takeover","points":164,"contributor_type":"quad_rank"},{"username":"GreedyHope3776","points":164,"contributor_type":"quad_rank"},{"username":"Hastyrunner245","points":624,"contributor_type":"quad_rank"},{"username":"mrcodehpr01","points":72,"contributor_type":"quad_rank"},{"username":"Miljenko-i-Manjina","points":399,"contributor_type":"quad_rank"},{"username":"VarenDerpsAround","points":120,"contributor_type":"quad_rank"},{"username":"tbroas","points":120,"contributor_type":"quad_rank"},{"username":"CheersBros","points":1465,"contributor_type":"quad_rank"},{"username":"smgnstr","points":2077,"contributor_type":"quad_rank"},{"username":"stedgyson","points":279,"contributor_type":"quad_rank"},{"username":"ZeroOne15","points":308,"contributor_type":"quad_rank"},{"username":"Apprehensive_Lie8179","points":279,"contributor_type":"quad_rank"},{"username":"Firm-Raise5017","points":279,"contributor_type":"quad_rank"},{"username":"ghochumal","points":1121,"contributor_type":"quad_rank"},{"username":"frade0911","points":279,"contributor_type":"quad_rank"},{"username":"hipcurved4","points":279,"contributor_type":"quad_rank"},{"username":"Shr00MN00B6","points":755,"contributor_type":"quad_rank"},{"username":"busyflughafen","points":279,"contributor_type":"quad_rank"},{"username":"Fritz1818","points":1656,"contributor_type":"quad_rank"},{"username":"ExternalOk4293","points":443,"contributor_type":"quad_rank"},{"username":"KaelinSC","points":279,"contributor_type":"quad_rank"},{"username":"littlehead13","points":279,"contributor_type":"quad_rank"},{"username":"watermeIonfelon","points":279,"contributor_type":"quad_rank"},{"username":"aula21un","points":443,"contributor_type":"quad_rank"},{"username":"MongooseMaleficent69","points":1356,"contributor_type":"quad_rank"},{"username":"annontraveler49","points":279,"contributor_type":"quad_rank"},{"username":"jeveuxalle","points":279,"contributor_type":"quad_rank"},{"username":"ElfriedeLantermany","points":680,"contributor_type":"quad_rank"},{"username":"CravinM1","points":558,"contributor_type":"quad_rank"},{"username":"KingBryandon","points":279,"contributor_type":"quad_rank"},{"username":"acidsiefer","points":120,"contributor_type":"quad_rank"},{"username":"Prollyfried","points":399,"contributor_type":"quad_rank"},{"username":"Jerry200px","points":154,"contributor_type":"quad_rank"},{"username":"Practical-Ferret-643","points":443,"contributor_type":"quad_rank"},{"username":"ethereumshield","points":164,"contributor_type":"quad_rank"},{"username":"caco3boy","points":443,"contributor_type":"quad_rank"},{"username":"MediaTrafficOrg","points":690,"contributor_type":"quad_rank"},{"username":"erza_nightwalker","points":279,"contributor_type":"quad_rank"},{"username":"wanpilaoban","points":279,"contributor_type":"quad_rank"},{"username":"HypenusDina","points":279,"contributor_type":"quad_rank"},{"username":"Orlandodaguy","points":279,"contributor_type":"quad_rank"},{"username":"LuckyLeverageTrader","points":842,"contributor_type":"quad_rank"},{"username":"4ever_blowingbubbles","points":279,"contributor_type":"quad_rank"},{"username":"Azcrael","points":279,"contributor_type":"quad_rank"},{"username":"Dabba-The-HuttOG","points":90,"contributor_type":"quad_rank"},{"username":"isthistomorrow_","points":369,"contributor_type":"quad_rank"},{"username":"SimpleSwapExchange","points":279,"contributor_type":"quad_rank"},{"username":"deathtolucky","points":279,"contributor_type":"quad_rank"},{"username":"Anna8600","points":399,"contributor_type":"quad_rank"},{"username":"royalewcheeze","points":279,"contributor_type":"quad_rank"},{"username":"Blattrech77","points":563,"contributor_type":"quad_rank"},{"username":"dilangkahxh","points":164,"contributor_type":"quad_rank"},{"username":"imjakedaniels","points":975,"contributor_type":"quad_rank"},{"username":"CryptoGenius_","points":896,"contributor_type":"quad_rank"},{"username":"DDDUnit2990","points":154,"contributor_type":"quad_rank"},{"username":"Laterxgater","points":279,"contributor_type":"quad_rank"},{"username":"chrisb1089","points":526,"contributor_type":"quad_rank"},{"username":"Budget-Buffalo-6804","points":797,"contributor_type":"quad_rank"},{"username":"MasterBurro","points":3476,"contributor_type":"quad_rank"},{"username":"Aevaron","points":279,"contributor_type":"quad_rank"},{"username":"MacTheNyfe","points":279,"contributor_type":"quad_rank"},{"username":"ExtraNoodlesPlz","points":279,"contributor_type":"quad_rank"},{"username":"10marketing8","points":279,"contributor_type":"quad_rank"},{"username":"woesofaho","points":279,"contributor_type":"quad_rank"},{"username":"Barbarossabros","points":279,"contributor_type":"quad_rank"},{"username":"LargeMain","points":367,"contributor_type":"quad_rank"},{"username":"Bergie008","points":191,"contributor_type":"quad_rank"},{"username":"Solodeji","points":617,"contributor_type":"quad_rank"},{"username":"chaseg22","points":666,"contributor_type":"quad_rank"},{"username":"Tylanmon","points":563,"contributor_type":"quad_rank"},{"username":"AlphaOne001","points":283,"contributor_type":"quad_rank"},{"username":"anon80788","points":447,"contributor_type":"quad_rank"},{"username":"Gurvir_","points":488,"contributor_type":"quad_rank"},{"username":"daviddme","points":164,"contributor_type":"quad_rank"},{"username":"rob5i","points":963,"contributor_type":"quad_rank"},{"username":"mikeoxlong_--","points":283,"contributor_type":"quad_rank"},{"username":"02attaxe","points":443,"contributor_type":"quad_rank"},{"username":"megselepgeci","points":164,"contributor_type":"quad_rank"},{"username":"DetroitMotorShow","points":164,"contributor_type":"quad_rank"},{"username":"Neat-Apartment3871","points":443,"contributor_type":"quad_rank"},{"username":"ArsenFirst","points":164,"contributor_type":"quad_rank"},{"username":"jayjay16022","points":164,"contributor_type":"quad_rank"},{"username":"Camlefff","points":443,"contributor_type":"quad_rank"},{"username":"ClarePerry","points":443,"contributor_type":"quad_rank"},{"username":"Sopongebob123","points":1060,"contributor_type":"quad_rank"},{"username":"C4-PO","points":283,"contributor_type":"quad_rank"},{"username":"Simple-Nebula3403","points":443,"contributor_type":"quad_rank"},{"username":"CryptoChillMedia","points":164,"contributor_type":"quad_rank"},{"username":"KevinRub","points":563,"contributor_type":"quad_rank"},{"username":"Brazilifia","points":279,"contributor_type":"quad_rank"},{"username":"coburn24","points":1840,"contributor_type":"quad_rank"},{"username":"whipsaw_","points":399,"contributor_type":"quad_rank"},{"username":"SoSoPatPat","points":399,"contributor_type":"quad_rank"},{"username":"codclark","points":399,"contributor_type":"quad_rank"},{"username":"matityboi","points":279,"contributor_type":"quad_rank"},{"username":"Delam2","points":279,"contributor_type":"quad_rank"},{"username":"ladderdensity2","points":1016,"contributor_type":"quad_rank"},{"username":"RogueMaven","points":399,"contributor_type":"quad_rank"},{"username":"abandoned_hotel","points":399,"contributor_type":"quad_rank"},{"username":"firerisk","points":797,"contributor_type":"quad_rank"},{"username":"Old_Afternoon3853","points":399,"contributor_type":"quad_rank"},{"username":"Wolfguarde_","points":399,"contributor_type":"quad_rank"},{"username":"NFT-master","points":399,"contributor_type":"quad_rank"},{"username":"TheReal-BKM","points":279,"contributor_type":"quad_rank"},{"username":"egglove48","points":399,"contributor_type":"quad_rank"},{"username":"Not-a-German","points":279,"contributor_type":"quad_rank"},{"username":"joskye","points":120,"contributor_type":"quad_rank"},{"username":"SolorMining","points":120,"contributor_type":"quad_rank"},{"username":"Sorry-Computer-9093","points":120,"contributor_type":"quad_rank"},{"username":"HistoricalPlane67","points":120,"contributor_type":"quad_rank"},{"username":"SeaworthinessFit1272","points":120,"contributor_type":"quad_rank"},{"username":"Zeeblackbaron","points":120,"contributor_type":"quad_rank"},{"username":"TumbleweedEmergency4","points":120,"contributor_type":"quad_rank"},{"username":"ledonskim754","points":120,"contributor_type":"quad_rank"},{"username":"smaudd","points":120,"contributor_type":"quad_rank"},{"username":"Soggy-Ad-5629","points":120,"contributor_type":"quad_rank"},{"username":"SouthernDependent388","points":120,"contributor_type":"quad_rank"},{"username":"OG-Cryptomaniac","points":120,"contributor_type":"quad_rank"},{"username":"kirkisartist","points":120,"contributor_type":"quad_rank"},{"username":"levi97zzz","points":120,"contributor_type":"quad_rank"},{"username":"sportifynews","points":120,"contributor_type":"quad_rank"},{"username":"amosrendao","points":120,"contributor_type":"quad_rank"},{"username":"Adventurous-Pay-8441","points":120,"contributor_type":"quad_rank"},{"username":"Iron_Defender","points":120,"contributor_type":"quad_rank"},{"username":"TheSilverBug","points":283,"contributor_type":"quad_rank"},{"username":"eaza00","points":283,"contributor_type":"quad_rank"},{"username":"invictum_","points":283,"contributor_type":"quad_rank"},{"username":"Dangerous_Try8644","points":366,"contributor_type":"quad_rank"},{"username":"SacredHam00","points":41,"contributor_type":"quad_rank"},{"username":"Jackson_Wills","points":205,"contributor_type":"quad_rank"},{"username":"Beautiful_Bar7462","points":120,"contributor_type":"quad_rank"},{"username":"h3lfw3yd3ad","points":120,"contributor_type":"quad_rank"},{"username":"Alexand0x","points":120,"contributor_type":"quad_rank"},{"username":"ro0tbrian","points":120,"contributor_type":"quad_rank"},{"username":"OkMongoose7304","points":120,"contributor_type":"quad_rank"},{"username":"meisjoee","points":120,"contributor_type":"quad_rank"},{"username":"rozodots","points":324,"contributor_type":"quad_rank"},{"username":"firgma","points":120,"contributor_type":"quad_rank"},{"username":"lowkeypicasso","points":120,"contributor_type":"quad_rank"},{"username":"arthropal","points":120,"contributor_type":"quad_rank"},{"username":"Odunayo20","points":120,"contributor_type":"quad_rank"},{"username":"LionRivr","points":120,"contributor_type":"quad_rank"},{"username":"elMoose99","points":120,"contributor_type":"quad_rank"},{"username":"WitchesAndMouses","points":120,"contributor_type":"quad_rank"},{"username":"MordvyVT","points":120,"contributor_type":"quad_rank"},{"username":"Minimum_Razzmatazz35","points":120,"contributor_type":"quad_rank"},{"username":"Ashrakk","points":120,"contributor_type":"quad_rank"},{"username":"Roninforcash","points":120,"contributor_type":"quad_rank"},{"username":"therdai","points":1314,"contributor_type":"quad_rank"},{"username":"CRPTN3WB","points":85,"contributor_type":"quad_rank"},{"username":"VCRdrift","points":164,"contributor_type":"quad_rank"},{"username":"WillianBo","points":164,"contributor_type":"quad_rank"},{"username":"shelfy1","points":164,"contributor_type":"quad_rank"},{"username":"tbigballer","points":205,"contributor_type":"quad_rank"},{"username":"Pristine_Problem_918","points":90,"contributor_type":"quad_rank"},{"username":"FortuitousAdroit","points":1069,"contributor_type":"quad_rank"},{"username":"SickTwist1971","points":164,"contributor_type":"quad_rank"},{"username":"Fit-Star-40","points":205,"contributor_type":"quad_rank"},{"username":"CorrineSomers","points":164,"contributor_type":"quad_rank"},{"username":"salty-bois","points":255,"contributor_type":"quad_rank"},{"username":"confuseduser12","points":91,"contributor_type":"quad_rank"},{"username":"GDawgs27","points":41,"contributor_type":"quad_rank"}]}