{"label":"round_128","startDate":1693429200,"endDate":1695848400,"count":[{"username":"economist_kinda","points":5,"donutFee":1250},{"username":"verysillyman","points":7,"donutFee":1750},{"username":"DeliveryWilling1396","points":13,"donutFee":3250},{"username":"kirtash93","points":8,"donutFee":2000},{"username":"StarchyEarning","points":3,"donutFee":750},{"username":"Mr-Rius","points":2,"donutFee":500},{"username":"Difficult_Bid_7470","points":1,"donutFee":250},{"username":"Fritz1818","points":3,"donutFee":750},{"username":"TheRealRel","points":1,"donutFee":250},{"username":"Snek-Life","points":3,"donutFee":750},{"username":"CommunityPoints","points":1,"donutFee":250},{"username":"Wonderful_Bad6531","points":6,"donutFee":1500},{"username":"DarkLoose199","points":2,"donutFee":500},{"username":"pythonskynet","points":29,"donutFee":7250},{"username":"SoulUrgeDestiny","points":1,"donutFee":250},{"username":"__deandre","points":1,"donutFee":250},{"username":"it0","points":1,"donutFee":250},{"username":"good2youall","points":2,"donutFee":500},{"username":"bzzking","points":2,"donutFee":500},{"username":"Odd_Service541","points":1,"donutFee":250},{"username":"Collectibl3","points":1,"donutFee":250},{"username":"aggressive_healer","points":3,"donutFee":750},{"username":"garysei124","points":6,"donutFee":1500},{"username":"Buzzalu","points":18,"donutFee":4500},{"username":"PotentialClassroom75","points":7,"donutFee":1750},{"username":"SantosTrahan","points":16,"donutFee":4000},{"username":"Only1Shock","points":5,"donutFee":1250},{"username":"Latter_Assistant_463","points":1,"donutFee":250},{"username":"Fearless_Ad_5938","points":1,"donutFee":250},{"username":"Dapper-Horror3112","points":17,"donutFee":4250},{"username":"Sybil_White","points":19,"donutFee":4750},{"username":"KM4WDK","points":4,"donutFee":1000},{"username":"KompolNakBroMek","points":7,"donutFee":1750},{"username":"na7oul","points":1,"donutFee":250},{"username":"JETTTZOR","points":1,"donutFee":250},{"username":"Zephyr023","points":2,"donutFee":500},{"username":"Gullible_Champion_41","points":7,"donutFee":1750},{"username":"teeceaustralia","points":6,"donutFee":1500},{"username":"Priyanka010","points":1,"donutFee":250},{"username":"Dondada001","points":1,"donutFee":250},{"username":"Funnyurolith61","points":1,"donutFee":250},{"username":"Allions1","points":4,"donutFee":1000},{"username":"NorthConcept9836","points":6,"donutFee":1500},{"username":"ethereum88","points":1,"donutFee":250},{"username":"raymv1987","points":4,"donutFee":1000},{"username":"Redeyukolo","points":1,"donutFee":250},{"username":"MarcelleMcintyre","points":1,"donutFee":250},{"username":"Daddio_87","points":1,"donutFee":250},{"username":"AutoModerator","points":7,"donutFee":1750},{"username":"This_is_a_Lamp","points":1,"donutFee":250},{"username":"tahiraslam8k","points":2,"donutFee":500},{"username":"EthTrader_Reposter","points":13,"donutFee":3250},{"username":"reddito321","points":5,"donutFee":1250},{"username":"rare1994","points":2,"donutFee":500},{"username":"Popular_Rub9075","points":1,"donutFee":250},{"username":"Roy1984","points":1,"donutFee":250},{"username":"Odlavso","points":3,"donutFee":750},{"username":"ToshiSat","points":3,"donutFee":750},{"username":"Petoruchosu","points":2,"donutFee":500},{"username":"tgold3461","points":1,"donutFee":250},{"username":"fc-test","points":2,"donutFee":500},{"username":"tambaybtc","points":2,"donutFee":500},{"username":"raresanevoice","points":3,"donutFee":750},{"username":"LtColumbo69","points":1,"donutFee":250},{"username":"Salt-Young","points":1,"donutFee":250},{"username":"No_Command606","points":1,"donutFee":250},{"username":"_Ovays_","points":1,"donutFee":250},{"username":"Adeolamhi1","points":2,"donutFee":500},{"username":"sidmehra1992","points":2,"donutFee":500},{"username":"RickyRichard26","points":9,"donutFee":2250},{"username":"Byte-Blaze","points":1,"donutFee":250},{"username":"Defiboy","points":1,"donutFee":250},{"username":"Prestospin","points":2,"donutFee":500},{"username":"imgracy","points":3,"donutFee":750},{"username":"Mysterious_massage","points":1,"donutFee":250},{"username":"Ashamed-Salary5692","points":4,"donutFee":1000},{"username":"salil19","points":1,"donutFee":250},{"username":"Fiddlers-list","points":3,"donutFee":750},{"username":"Scholar2001","points":4,"donutFee":1000},{"username":"davidahoffman","points":1,"donutFee":250},{"username":"Soaring_Eagle590","points":6,"donutFee":1500},{"username":"uzochi123","points":2,"donutFee":500},{"username":"mellon98","points":1,"donutFee":250},{"username":"cashapat18","points":1,"donutFee":250},{"username":"DiiDantes","points":1,"donutFee":250},{"username":"dellarangel7","points":1,"donutFee":250},{"username":"TomikoHerrmann","points":2,"donutFee":500},{"username":"CaterinaTurpin","points":3,"donutFee":750},{"username":"toogoodtgp","points":1,"donutFee":250},{"username":"ASingleGuitarString","points":4,"donutFee":1000},{"username":"thetriplem21","points":4,"donutFee":1000},{"username":"rootpl","points":1,"donutFee":250},{"username":"CarolaWinfrey","points":1,"donutFee":250},{"username":"MrDexterX","points":2,"donutFee":500},{"username":"LivingFondant1419","points":2,"donutFee":500},{"username":"samrickers_","points":1,"donutFee":250},{"username":"cointelegraph1","points":2,"donutFee":500},{"username":"Negative-Structure51","points":2,"donutFee":500},{"username":"stunningascism","points":1,"donutFee":250},{"username":"CharlieDLg","points":1,"donutFee":250},{"username":"iamjide91","points":1,"donutFee":250},{"username":"Every_Hunt_160","points":2,"donutFee":500},{"username":"FabulousInvestment32","points":1,"donutFee":250},{"username":"CriticalGardena","points":1,"donutFee":250},{"username":"yester_philippines","points":3,"donutFee":750},{"username":"terry_lee_barton","points":3,"donutFee":750},{"username":"Jealous_Type_3480","points":3,"donutFee":750},{"username":"Amritfintrades","points":1,"donutFee":250},{"username":"happily_unlawful","points":4,"donutFee":1000},{"username":"pizzapicnic","points":1,"donutFee":250},{"username":"AltruisticPops","points":1,"donutFee":250},{"username":"sadsissyphus","points":6,"donutFee":1500},{"username":"Samir2298","points":1,"donutFee":250},{"username":"whodontloveboobs","points":3,"donutFee":750},{"username":"Interesting-Chip-500","points":1,"donutFee":250},{"username":"Acceptable-Sort-8429","points":2,"donutFee":500},{"username":"LesserBucket","points":1,"donutFee":250},{"username":"Fataltc2002","points":2,"donutFee":500},{"username":"Gubbie99","points":2,"donutFee":500},{"username":"TheNano100","points":2,"donutFee":500},{"username":"Zealousideal_Ice8918","points":4,"donutFee":1000},{"username":"noob_zarathustra","points":2,"donutFee":500},{"username":"aadhar690","points":1,"donutFee":250},{"username":"FarMangement","points":1,"donutFee":250},{"username":"BausOfBacon","points":1,"donutFee":250},{"username":"HarryDotter420","points":3,"donutFee":750},{"username":"blacktheology36","points":2,"donutFee":500},{"username":"DreadLocksHippie","points":1,"donutFee":250},{"username":"clean_cut89","points":1,"donutFee":250},{"username":"indian_beardo","points":2,"donutFee":500},{"username":"cacophany_of_silence","points":1,"donutFee":250},{"username":"Sunryzen","points":2,"donutFee":500},{"username":"TheMadHawk2212","points":1,"donutFee":250},{"username":"DasPanzer1939-1945","points":3,"donutFee":750},{"username":"Onion-Acrobatic","points":1,"donutFee":250},{"username":"Pacaloz","points":1,"donutFee":250},{"username":"shoaib_ahmed_007","points":7,"donutFee":1750},{"username":"LengthinessConnect38","points":1,"donutFee":250},{"username":"proandromeda","points":2,"donutFee":500},{"username":"Willwalt","points":4,"donutFee":1000},{"username":"0huey0","points":1,"donutFee":250},{"username":"frange2020","points":2,"donutFee":500},{"username":"Jadencool15","points":2,"donutFee":500},{"username":"pprojams","points":1,"donutFee":250},{"username":"Superdevman69","points":4,"donutFee":1000},{"username":"letsridetheworld","points":1,"donutFee":250},{"username":"Scurvywaif4","points":1,"donutFee":250},{"username":"Catwednesday","points":2,"donutFee":500},{"username":"goldyluckinblokchain","points":1,"donutFee":250},{"username":"bradlux01","points":1,"donutFee":250},{"username":"Atyzze","points":3,"donutFee":750},{"username":"TombMaster1","points":1,"donutFee":250},{"username":"cryptopunk661","points":1,"donutFee":250},{"username":"SufficintHope","points":4,"donutFee":1000},{"username":"babyjessica23","points":1,"donutFee":250},{"username":"o_LUCIFER_o","points":1,"donutFee":250},{"username":"SuperbCantaloupe1929","points":1,"donutFee":250},{"username":"scicon5","points":3,"donutFee":750},{"username":"aminok","points":3,"donutFee":750},{"username":"Embarrassed_Chef_393","points":2,"donutFee":500},{"username":"Super_Iron6408","points":2,"donutFee":500},{"username":"LinedVaccination","points":1,"donutFee":250},{"username":"Excellent-Lecture-45","points":1,"donutFee":250},{"username":"matsumoto_iyo","points":1,"donutFee":250},{"username":"abcoathup","points":1,"donutFee":250},{"username":"SignificantProduce48","points":1,"donutFee":250},{"username":"Bucksaway03","points":1,"donutFee":250},{"username":"usasmmit07","points":1,"donutFee":250},{"username":"lamo_pdf25","points":4,"donutFee":1000},{"username":"wrestler2003","points":1,"donutFee":250},{"username":"sleepy-panda521","points":1,"donutFee":250},{"username":"_Mastermojo_","points":2,"donutFee":500},{"username":"Bashir_Jasper03","points":1,"donutFee":250},{"username":"pikmin969","points":1,"donutFee":250},{"username":"Eru_Iluvatarh","points":1,"donutFee":250},{"username":"jackdawsenrobersn44","points":3,"donutFee":750},{"username":"Security_Raven","points":1,"donutFee":250},{"username":"Kindly-Wolf6919","points":1,"donutFee":250},{"username":"djquimoso","points":1,"donutFee":250},{"username":"TailsOnTilt","points":5,"donutFee":1250},{"username":"DrProfitCrypto","points":1,"donutFee":250},{"username":"bdinu89","points":1,"donutFee":250},{"username":"NSFWCryptoPosting","points":2,"donutFee":500},{"username":"Savi321","points":1,"donutFee":250},{"username":"dont_agree_with_me","points":2,"donutFee":500},{"username":"greenpepperhypernova","points":1,"donutFee":250},{"username":"Zealousideal-Arm420","points":1,"donutFee":250},{"username":"AverageRedditLad","points":1,"donutFee":250},{"username":"83nno","points":1,"donutFee":250},{"username":"robnectar","points":1,"donutFee":250},{"username":"Queengenademedicieth","points":2,"donutFee":500},{"username":"Monster_Chief17","points":1,"donutFee":250},{"username":"Beginning_Yak_4632","points":1,"donutFee":250},{"username":"Harold838383","points":1,"donutFee":250},{"username":"Lucky_Letter_2730","points":1,"donutFee":250},{"username":"cryptbunks","points":1,"donutFee":250},{"username":"Goldman_Duck","points":1,"donutFee":250},{"username":"tetheqpi","points":1,"donutFee":250},{"username":"Simple_Mastodon9220","points":1,"donutFee":250},{"username":"AlexisJOwns","points":1,"donutFee":250},{"username":"FicklePhilosophy","points":1,"donutFee":250},{"username":"EmilyLovs","points":1,"donutFee":250},{"username":"bordoisse","points":1,"donutFee":250},{"username":"extraboldscowsj28","points":1,"donutFee":250},{"username":"mentalgooseflesh","points":1,"donutFee":250},{"username":"PublicSleeper","points":1,"donutFee":250},{"username":"SamaraSponsoao","points":2,"donutFee":500},{"username":"FalloutAssasin","points":1,"donutFee":250}]}